[
    {
        "FilterGroup": 0,
        "FilterOperator": "=",
        "FilterValue": "'Applicant'",
        "GlobalKey": "RFExtractGetApplicantNameCustom7593",
        "InputFieldName": "ApplicantType__c",
        "InputObjectName": "RF_Applicant__c",
        "InputObjectQuerySequence": 1,
        "IsDisabled": false,
        "IsRequiredForUpsert": false,
        "IsUpsertKey": false,
        "Name": "RFExtractGetApplicantName",
        "OmniDataTransformationId": {
            "Name": "RFExtractGetApplicantName",
            "VlocityDataPackType": "VlocityMatchingKeyObject",
            "VlocityMatchingRecordSourceKey": "OmniDataTransform/RFExtractGetApplicantName",
            "VlocityRecordSObjectType": "OmniDataTransform"
        },
        "OutputCreationSequence": 0,
        "OutputFieldName": "Applicant",
        "OutputObjectName": "json",
        "VlocityDataPackType": "SObject",
        "VlocityRecordSObjectType": "OmniDataTransformItem"
    },
    {
        "FilterGroup": 0,
        "FilterOperator": "=",
        "FilterValue": "ApplicationId",
        "GlobalKey": "RFExtractGetApplicantName7377381827966707",
        "InputFieldName": "ApplicationId__c",
        "InputObjectName": "RF_Applicant__c",
        "InputObjectQuerySequence": 1,
        "IsDisabled": false,
        "IsRequiredForUpsert": false,
        "IsUpsertKey": false,
        "Name": "RFExtractGetApplicantName",
        "OmniDataTransformationId": {
            "Name": "RFExtractGetApplicantName",
            "VlocityDataPackType": "VlocityMatchingKeyObject",
            "VlocityMatchingRecordSourceKey": "OmniDataTransform/RFExtractGetApplicantName",
            "VlocityRecordSObjectType": "OmniDataTransform"
        },
        "OutputCreationSequence": 0,
        "OutputFieldName": "Applicant",
        "OutputObjectName": "json",
        "VlocityDataPackType": "SObject",
        "VlocityRecordSObjectType": "OmniDataTransformItem"
    },
    {
        "GlobalKey": "RFExtractGetApplicantName5403213781264797",
        "InputFieldName": "Applicant:Name",
        "IsDisabled": false,
        "IsRequiredForUpsert": false,
        "IsUpsertKey": false,
        "Name": "RFExtractGetApplicantName",
        "OmniDataTransformationId": {
            "Name": "RFExtractGetApplicantName",
            "VlocityDataPackType": "VlocityMatchingKeyObject",
            "VlocityMatchingRecordSourceKey": "OmniDataTransform/RFExtractGetApplicantName",
            "VlocityRecordSObjectType": "OmniDataTransform"
        },
        "OutputCreationSequence": 1,
        "OutputFieldName": "ApplicantName",
        "OutputObjectName": "json",
        "VlocityDataPackType": "SObject",
        "VlocityRecordSObjectType": "OmniDataTransformItem"
    }
]