[
    {
        "FormulaExpression": "CONCAT(FirstName,' ',LastName)",
        "FormulaResultPath": "FFullName",
        "FormulaSequence": 1,
        "GlobalKey": "RFLoadUpsertReferenceCustom6367",
        "IsDisabled": false,
        "IsRequiredForUpsert": false,
        "IsUpsertKey": false,
        "Name": "RFLoadUpsertReference",
        "OmniDataTransformationId": {
            "Name": "RFLoadUpsertReference",
            "VlocityDataPackType": "VlocityMatchingKeyObject",
            "VlocityMatchingRecordSourceKey": "OmniDataTransform/RFLoadUpsertReference",
            "VlocityRecordSObjectType": "OmniDataTransform"
        },
        "OutputCreationSequence": 0,
        "OutputFieldName": "Formula",
        "OutputObjectName": "Formula",
        "VlocityDataPackType": "SObject",
        "VlocityRecordSObjectType": "OmniDataTransformItem"
    },
    {
        "GlobalKey": "RFLoadUpsertReferenceCustom2145",
        "InputFieldName": "PrimaryApplicantId",
        "IsDisabled": false,
        "IsRequiredForUpsert": false,
        "IsUpsertKey": false,
        "Name": "RFLoadUpsertReference",
        "OmniDataTransformationId": {
            "Name": "RFLoadUpsertReference",
            "VlocityDataPackType": "VlocityMatchingKeyObject",
            "VlocityMatchingRecordSourceKey": "OmniDataTransform/RFLoadUpsertReference",
            "VlocityRecordSObjectType": "OmniDataTransform"
        },
        "OutputCreationSequence": 1,
        "OutputFieldName": "Account__c",
        "OutputObjectName": "RF_References__c",
        "VlocityDataPackType": "SObject",
        "VlocityRecordSObjectType": "OmniDataTransformItem"
    },
    {
        "GlobalKey": "RFLoadUpsertReferenceCustom7084",
        "InputFieldName": "ReferenceId",
        "IsDisabled": false,
        "IsRequiredForUpsert": false,
        "IsUpsertKey": true,
        "Name": "RFLoadUpsertReference",
        "OmniDataTransformationId": {
            "Name": "RFLoadUpsertReference",
            "VlocityDataPackType": "VlocityMatchingKeyObject",
            "VlocityMatchingRecordSourceKey": "OmniDataTransform/RFLoadUpsertReference",
            "VlocityRecordSObjectType": "OmniDataTransform"
        },
        "OutputCreationSequence": 1,
        "OutputFieldName": "Id",
        "OutputObjectName": "RF_References__c",
        "VlocityDataPackType": "SObject",
        "VlocityRecordSObjectType": "OmniDataTransformItem"
    },
    {
        "FilterOperator": "=",
        "GlobalKey": "RFLoadUpsertReferenceCustom9943",
        "IsDisabled": true,
        "IsRequiredForUpsert": false,
        "IsUpsertKey": false,
        "MigrationValue": "FAKEMAPPING",
        "Name": "RFLoadUpsertReference",
        "OmniDataTransformationId": {
            "Name": "RFLoadUpsertReference",
            "VlocityDataPackType": "VlocityMatchingKeyObject",
            "VlocityMatchingRecordSourceKey": "OmniDataTransform/RFLoadUpsertReference",
            "VlocityRecordSObjectType": "OmniDataTransform"
        },
        "OutputCreationSequence": 1,
        "OutputFieldName": "Id",
        "OutputObjectName": "RF_References__c",
        "VlocityDataPackType": "SObject",
        "VlocityRecordSObjectType": "OmniDataTransformItem"
    },
    {
        "GlobalKey": "RFLoadUpsertReferenceCustom1294",
        "InputFieldName": "LoanContractId",
        "IsDisabled": false,
        "IsRequiredForUpsert": false,
        "IsUpsertKey": false,
        "Name": "RFLoadUpsertReference",
        "OmniDataTransformationId": {
            "Name": "RFLoadUpsertReference",
            "VlocityDataPackType": "VlocityMatchingKeyObject",
            "VlocityMatchingRecordSourceKey": "OmniDataTransform/RFLoadUpsertReference",
            "VlocityRecordSObjectType": "OmniDataTransform"
        },
        "OutputCreationSequence": 1,
        "OutputFieldName": "RF_Financial_Account__c",
        "OutputObjectName": "RF_References__c",
        "VlocityDataPackType": "SObject",
        "VlocityRecordSObjectType": "OmniDataTransformItem"
    },
    {
        "GlobalKey": "RFLoadUpsertReferenceCustom1536",
        "InputFieldName": "FirstName",
        "IsDisabled": false,
        "IsRequiredForUpsert": false,
        "IsUpsertKey": false,
        "Name": "RFLoadUpsertReference",
        "OmniDataTransformationId": {
            "Name": "RFLoadUpsertReference",
            "VlocityDataPackType": "VlocityMatchingKeyObject",
            "VlocityMatchingRecordSourceKey": "OmniDataTransform/RFLoadUpsertReference",
            "VlocityRecordSObjectType": "OmniDataTransform"
        },
        "OutputCreationSequence": 1,
        "OutputFieldName": "RF_First_Name__c",
        "OutputObjectName": "RF_References__c",
        "VlocityDataPackType": "SObject",
        "VlocityRecordSObjectType": "OmniDataTransformItem"
    },
    {
        "GlobalKey": "RFLoadUpsertReferenceCustom772",
        "InputFieldName": "FFullName",
        "IsDisabled": false,
        "IsRequiredForUpsert": false,
        "IsUpsertKey": false,
        "Name": "RFLoadUpsertReference",
        "OmniDataTransformationId": {
            "Name": "RFLoadUpsertReference",
            "VlocityDataPackType": "VlocityMatchingKeyObject",
            "VlocityMatchingRecordSourceKey": "OmniDataTransform/RFLoadUpsertReference",
            "VlocityRecordSObjectType": "OmniDataTransform"
        },
        "OutputCreationSequence": 1,
        "OutputFieldName": "RF_Full_Name__c",
        "OutputObjectName": "RF_References__c",
        "VlocityDataPackType": "SObject",
        "VlocityRecordSObjectType": "OmniDataTransformItem"
    },
    {
        "GlobalKey": "RFLoadUpsertReferenceCustom8450",
        "InputFieldName": "LastName",
        "IsDisabled": false,
        "IsRequiredForUpsert": false,
        "IsUpsertKey": false,
        "Name": "RFLoadUpsertReference",
        "OmniDataTransformationId": {
            "Name": "RFLoadUpsertReference",
            "VlocityDataPackType": "VlocityMatchingKeyObject",
            "VlocityMatchingRecordSourceKey": "OmniDataTransform/RFLoadUpsertReference",
            "VlocityRecordSObjectType": "OmniDataTransform"
        },
        "OutputCreationSequence": 1,
        "OutputFieldName": "RF_Last_Name__c",
        "OutputObjectName": "RF_References__c",
        "VlocityDataPackType": "SObject",
        "VlocityRecordSObjectType": "OmniDataTransformItem"
    },
    {
        "GlobalKey": "RFLoadUpsertReferenceCustom2249",
        "InputFieldName": "Phone",
        "IsDisabled": false,
        "IsRequiredForUpsert": false,
        "IsUpsertKey": false,
        "Name": "RFLoadUpsertReference",
        "OmniDataTransformationId": {
            "Name": "RFLoadUpsertReference",
            "VlocityDataPackType": "VlocityMatchingKeyObject",
            "VlocityMatchingRecordSourceKey": "OmniDataTransform/RFLoadUpsertReference",
            "VlocityRecordSObjectType": "OmniDataTransform"
        },
        "OutputCreationSequence": 1,
        "OutputFieldName": "RF_Phone__c",
        "OutputObjectName": "RF_References__c",
        "VlocityDataPackType": "SObject",
        "VlocityRecordSObjectType": "OmniDataTransformItem"
    },
    {
        "GlobalKey": "RFLoadUpsertReferenceCustom5508",
        "InputFieldName": "Relationship",
        "IsDisabled": false,
        "IsRequiredForUpsert": false,
        "IsUpsertKey": false,
        "Name": "RFLoadUpsertReference",
        "OmniDataTransformationId": {
            "Name": "RFLoadUpsertReference",
            "VlocityDataPackType": "VlocityMatchingKeyObject",
            "VlocityMatchingRecordSourceKey": "OmniDataTransform/RFLoadUpsertReference",
            "VlocityRecordSObjectType": "OmniDataTransform"
        },
        "OutputCreationSequence": 1,
        "OutputFieldName": "Relationship__c",
        "OutputObjectName": "RF_References__c",
        "VlocityDataPackType": "SObject",
        "VlocityRecordSObjectType": "OmniDataTransformItem"
    }
]